opf_dataset_utils/__init__.py
opf_dataset_utils/costs.py
opf_dataset_utils/data/__init__.py
opf_dataset_utils/data/loading.py
opf_dataset_utils/data/subgraph_sampling.py
opf_dataset_utils/enumerations.py
opf_dataset_utils/physics/__init__.py
opf_dataset_utils/physics/errors/__init__.py
opf_dataset_utils/physics/errors/inequality/__init__.py
opf_dataset_utils/physics/errors/inequality/branch_power.py
opf_dataset_utils/physics/errors/inequality/generator_power.py
opf_dataset_utils/physics/errors/inequality/violations.py
opf_dataset_utils/physics/errors/inequality/voltage.py
opf_dataset_utils/physics/errors/power_flow.py
opf_dataset_utils/physics/power.py
opf_dataset_utils/physics/utils.py
opf_dataset_utils/physics/voltage.py
opf_dataset_utils/plotting/__init__.py
opf_dataset_utils/plotting/draw.py
opf_dataset_utils/plotting/utils.py
opf_dataset_utils-0.0.2.dist-info/LICENSE
opf_dataset_utils-0.0.2.dist-info/METADATA
opf_dataset_utils-0.0.2.dist-info/WHEEL
opf_dataset_utils-0.0.2.dist-info/entry_points.txt
opf_dataset_utils-0.0.2.dist-info/RECORD
