Metadata-Version: 2.1
Name: opf_dataset_utils
Version: 0.0.2
Summary: Physical calculations, plotting, and other utils for the PyG OPFDataset.
Author: Viktor Todosijevic
Author-email: todosijevicviktor998@gmail.com
Requires-Python: >=3.10,<3.12
Classifier: Programming Language :: Python :: 3
Classifier: Programming Language :: Python :: 3.10
Classifier: Programming Language :: Python :: 3.11
Requires-Dist: matplotlib (>=3.9.0,<4.0.0)
Requires-Dist: numpy (==1.26.0)
Requires-Dist: pydot (>=3.0.2,<4.0.0)
